Metadata-Version: 2.1
Name: trio-socks
Version: 0.1.1.post5
Summary: trio-socks provides a trio.abc.HalfCloseableStream that routes its traffic through a SOCKS proxy server
Home-page: https://github.com/Ostoic/trio-socks
Author: Shaun Ostoic
Author-email: shaun.ostoic@gmail.com
License: MIT
Download-URL: https://github.com/Ostoic/trio-socks/archive/v0.1.1-5.tar.gz
Keywords: socks5,trio-socks,trio
Platform: UNKNOWN
Classifier: Development Status :: 3 - Alpha
Classifier: Intended Audience :: Developers
Classifier: License :: OSI Approved :: MIT License
Classifier: Programming Language :: Python :: 3
Classifier: Programming Language :: Python :: 3.6
Classifier: Topic :: Software Development :: Libraries
Classifier: Framework :: Trio
Classifier: Topic :: System :: Networking
